camerge/__init__.py
camerge-0.0.3.dist-info/LICENSE
camerge-0.0.3.dist-info/METADATA
camerge-0.0.3.dist-info/WHEEL
camerge-0.0.3.dist-info/top_level.txt
camerge-0.0.3.dist-info/RECORD
