Metadata-Version: 2.1
Name: camerge
Version: 0.0.3
Summary: Merge multiple ical/ics calendars to one.
Home-page: https://github.com/LukasForst/camerge
Author: Lukas Forst
Author-email: lukas@forst.dev
Project-URL: Bug Reports, https://github.com/LukasForst/camerge/issues
Project-URL: Source, https://github.com/LukasForst/camerge
Keywords: calendar calendaring ical icalendar merge calendar-merge anonymization
Classifier: Development Status :: 4 - Beta
Classifier: Intended Audience :: Developers
Classifier: Operating System :: OS Independent
Classifier: License :: OSI Approved :: MIT License
Classifier: Programming Language :: Python :: 3.7
Classifier: Programming Language :: Python :: 3.8
Classifier: Programming Language :: Python :: 3.9
Classifier: Programming Language :: Python :: 3.10
Classifier: Programming Language :: Python :: 3.11
Requires-Python: >=3.7, <4
License-File: LICENSE
Requires-Dist: icalendar (>=4.1.0)
Provides-Extra: dev
Requires-Dist: check-manifest ; extra == 'dev'
Provides-Extra: test
Requires-Dist: coverage ; extra == 'test'
